paddlecraft/__init__.py
paddlecraft/base.py
paddlecraft/bert.py
paddlecraft/image_mlp_encoder.py
paddlecraft/transformer_encoder.py
paddlecraft/utils/__init__.py
paddlecraft/utils/configure.py
paddlecraft/utils/shared_tools.py
paddlecraft-0.0.2.dist-info/DESCRIPTION.rst
paddlecraft-0.0.2.dist-info/METADATA
paddlecraft-0.0.2.dist-info/RECORD
paddlecraft-0.0.2.dist-info/WHEEL
paddlecraft-0.0.2.dist-info/metadata.json
paddlecraft-0.0.2.dist-info/top_level.txt
