Metadata-Version: 2.0
Name: paddlecraft
Version: 0.0.2
Summary: Make Neural Models as APIs for solving more complicated AI problems
Home-page: https://github.com/PaddlePadd
Author: PaddlePaddle
Author-email: zhouxiangyang@baidu.com
License: Apache 2.0
Platform: any
Classifier: License :: OSI Approved :: Apache Software License
Classifier: Programming Language :: Python
Classifier: Programming Language :: Python :: 2
Classifier: Programming Language :: Python :: 2.7
Classifier: Programming Language :: Python :: 3
Classifier: Programming Language :: Python :: 3.5
Classifier: Programming Language :: Python :: 3.6
Classifier: Programming Language :: Python :: 3.7
